quickllm/__init__.py
quickllm/chat.py
quickllm/finetune.py
quickllm/gui.py
quickllm/models.py
quickllm/utils.py
quickllm/visualize.py
quickllm-1.0.1.dist-info/LICENSE
quickllm-1.0.1.dist-info/METADATA
quickllm-1.0.1.dist-info/WHEEL
quickllm-1.0.1.dist-info/top_level.txt
quickllm-1.0.1.dist-info/RECORD
