Metadata-Version: 2.1
Name: quickllm
Version: 1.0.1
Summary: A library for quick fine-tuning and interaction with popular language models
Home-page: https://github.com/yadavsidhant/quickllm
Author: Sidhant Yadav
Author-email: supersidhant10@gmail.com
License: UNKNOWN
Project-URL: Bug Tracker, https://github.com/yadavsidhant/quickllm/issues
Project-URL: Documentation, https://github.com/yadavsidhant/quickllm#readme
Project-URL: Youtube, https://www.youtube.com/@SidhantKYadav
Platform: UNKNOWN
Classifier: Programming Language :: Python :: 3
Classifier: License :: OSI Approved :: MIT License
Classifier: Operating System :: OS Independent
Requires-Python: >=3.7
License-File: LICENSE
Requires-Dist: transformers>=4.0.0
Requires-Dist: torch>=1.0.0
Requires-Dist: pandas>=1.0.0
Requires-Dist: matplotlib>=3.0.0
Requires-Dist: seaborn>=0.11.0
Requires-Dist: datasets>=1.0.0
Requires-Dist: colorama
Requires-Dist: PyQt5
Requires-Dist: peft
